netron/__init__.py
netron/__version__.py
netron/acuity-metadata.json
netron/acuity.js
netron/armnn-metadata.json
netron/armnn-schema.js
netron/armnn.js
netron/barracuda.js
netron/base.js
netron/bigdl-metadata.json
netron/bigdl-proto.js
netron/bigdl.js
netron/caffe-metadata.json
netron/caffe-proto.js
netron/caffe.js
netron/caffe2-metadata.json
netron/caffe2-proto.js
netron/caffe2.js
netron/circle-metadata.json
netron/circle-schema.js
netron/circle.js
netron/cntk-metadata.json
netron/cntk-proto.js
netron/cntk.js
netron/coreml-metadata.json
netron/coreml-proto.js
netron/coreml.js
netron/dagre.js
netron/darknet-metadata.json
netron/darknet.js
netron/dl4j-metadata.json
netron/dl4j.js
netron/dlc-schema.js
netron/dlc.js
netron/dnn-metadata.json
netron/dnn-proto.js
netron/dnn.js
netron/favicon.ico
netron/flatbuffers.js
netron/flax.js
netron/flexbuffers.js
netron/flux-metadata.json
netron/flux.js
netron/gzip.js
netron/hdf5.js
netron/icon.png
netron/imgdnn.js
netron/index.html
netron/index.js
netron/json.js
netron/keras-metadata.json
netron/keras.js
netron/kmodel.js
netron/lasagne-metadata.json
netron/lasagne.js
netron/lightgbm.js
netron/mediapipe.js
netron/mlnet-metadata.json
netron/mlnet.js
netron/mnn-metadata.json
netron/mnn-schema.js
netron/mnn.js
netron/msgpack.js
netron/mslite-metadata.json
netron/mslite-schema.js
netron/mslite.js
netron/mxnet-metadata.json
netron/mxnet.js
netron/ncnn-metadata.json
netron/ncnn.js
netron/nnabla-metadata.json
netron/nnabla-proto.js
netron/nnabla.js
netron/numpy.js
netron/om-metadata.json
netron/om-proto.js
netron/om.js
netron/onnx-metadata.json
netron/onnx-proto.js
netron/onnx-schema.js
netron/onnx.js
netron/openvino-metadata.json
netron/openvino.js
netron/paddle-metadata.json
netron/paddle-proto.js
netron/paddle-schema.js
netron/paddle.js
netron/pickle.js
netron/protobuf.js
netron/python.js
netron/pytorch-metadata.json
netron/pytorch.js
netron/rknn-metadata.json
netron/rknn.js
netron/server.py
netron/sklearn-metadata.json
wnetron-5.8.1.dist-info/LICENSE
wnetron-5.8.1.dist-info/METADATA
wnetron-5.8.1.dist-info/WHEEL
wnetron-5.8.1.dist-info/entry_points.txt
wnetron-5.8.1.dist-info/top_level.txt
wnetron-5.8.1.dist-info/RECORD
